{
  "timestamp": "2026-05-04T14:40:36",
  "pak": "build/MicrosoftAzureAdapter_8.19.13.pak",
  "sample": 30,
  "connection": "<connection>",
  "live": {
    "duration": 584.0791115760803,
    "total_objects": 2845,
    "kind_counts": {
      "azure_subscription": 6,
      "AZURE_RESOURCE_GROUP": 528,
      "AZURE_VIRTUAL_MACHINE": 219,
      "AZURE_DEDICATE_HOST": 10,
      "AZURE_STORAGE_DISK": 180,
      "AZURE_NW_INTERFACE": 159,
      "AZURE_VIRTUAL_NETWORK": 44,
      "azure_subnet": 338,
      "AZURE_STORAGE_ACCOUNT": 153,
      "AZURE_LB": 31,
      "AZURE_KEY_VAULTS": 86,
      "AZURE_SQL_SERVER": 12,
      "AZURE_SQL_DATABASE": 76,
      "AZURE_APP_SERVICE": 6,
      "AZURE_FUNCTIONS_APP": 2,
      "AZURE_APP_SERVICE_PLAN": 6,
      "AZURE_MYSQL_SERVER": 5,
      "AZURE_COMPUTE_HOSTGROUPS": 1,
      "AZURE_PUBLIC_IPADDRESSES": 23,
      "AZURE_EXPRESSROUTE_CIRCUITS": 3,
      "azure_recovery_services_vault": 110,
      "azure_log_analytics_workspace": 25,
      "AZURE_NETWORK_SECURITY_GROUP": 101,
      "AZURE_ROUTE_TABLES": 79,
      "AZURE_DNS_ZONES": 2,
      "AZURE_PRIVATE_DNSZONES": 82,
      "AZURE_FIREWALLS": 3,
      "AZURE_VIRTUAL_NETWORK_GATEWAY": 2,
      "AZURE_APPLICATION_GATEWAY": 1,
      "AZURE_VIRTUAL_HUBS": 2,
      "AZURE_NETWORK_WATCHERS": 13,
      "AZURE_KUBERNATE_CLUSTER": 9,
      "AZURE_CONTAINER_REGISTRIES": 6,
      "AZURE_VIRTUAL_SCALESET": 54,
      "AZURE_AVAILABILITY_SETS": 16,
      "AZURE_AUTOMATION": 20,
      "AZURE_CACHE_REDIS": 4,
      "AZURE_SQL_MANAGEDINSTANCES": 1,
      "AZURE_EVENTHUBS_NAMESPACES": 5,
      "AZURE_DATA_FACTORY": 2,
      "AZURE_DATA_EXPLORER_CLUSTER": 1,
      "AZURE_COGNITIVE_SERVICES_ACCOUNTS": 3,
      "azure_logic_workflow": 2,
      "azure_arc_machine": 53,
      "azure_bastion_host": 1,
      "azure_private_endpoint": 75,
      "azure_nat_gateway": 3,
      "azure_compute_snapshot": 117,
      "azure_disk_encryption_set": 47,
      "azure_managed_identity": 54,
      "azure_dns_resolver": 9,
      "azure_backup_vault": 1,
      "azure_sql_virtual_machine": 39,
      "azure_app_service_environment": 1,
      "azure_storage_sync": 1,
      "AZURE_REGION": 6,
      "AZURE_REGION_PER_SUB": 6,
      "AZURE_WORLD": 1
    },
    "kind_counts_unspecified": {
      "AZURE_NETWORK_SECURITY_GROUP": 101,
      "AZURE_ROUTE_TABLES": 79,
      "AZURE_DNS_ZONES": 2,
      "AZURE_PRIVATE_DNSZONES": 82,
      "AZURE_FIREWALLS": 3,
      "AZURE_VIRTUAL_NETWORK_GATEWAY": 2,
      "AZURE_APPLICATION_GATEWAY": 1,
      "AZURE_VIRTUAL_HUBS": 2,
      "AZURE_KUBERNATE_CLUSTER": 9,
      "AZURE_CONTAINER_REGISTRIES": 6,
      "AZURE_AUTOMATION": 20,
      "AZURE_CACHE_REDIS": 4,
      "AZURE_DATA_FACTORY": 2
    },
    "per_kind": {
      "azure_subscription": {
        "status": "PASS",
        "count": 6,
        "reasons": []
      },
      "AZURE_RESOURCE_GROUP": {
        "status": "PASS",
        "count": 528,
        "reasons": []
      },
      "AZURE_VIRTUAL_MACHINE": {
        "status": "PASS",
        "count": 219,
        "reasons": []
      },
      "AZURE_STORAGE_DISK": {
        "status": "PASS",
        "count": 180,
        "reasons": []
      },
      "AZURE_COMPUTE_HOSTGROUPS": {
        "status": "PASS",
        "count": 1,
        "reasons": []
      },
      "AZURE_DEDICATE_HOST": {
        "status": "FAIL",
        "count": 10,
        "reasons": [
          "10/10 missing parent AZURE_COMPUTE_HOSTGROUPS",
          "prop 'hourly_rate' not populated on any object",
          "prop 'host_vcpu_capacity' not populated on any object",
          "prop 'policy_compliance_state' not populated on any object",
          "prop 'memory_utilization_pct' not populated on any object",
          "prop 'monthly_rate_estimate' not populated on any object",
          "prop 'health_availability_state' not populated on any object",
          "prop 'SERVICE_DESCRIPTORS|AZURE_SUBSCRIPTION_ID' not populated on any object",
          "prop 'vm_size_summary' not populated on any object"
        ]
      },
      "AZURE_NW_INTERFACE": {
        "status": "PASS",
        "count": 159,
        "reasons": []
      },
      "AZURE_VIRTUAL_NETWORK": {
        "status": "PASS",
        "count": 44,
        "reasons": []
      },
      "azure_subnet": {
        "status": "PASS",
        "count": 338,
        "reasons": []
      },
      "AZURE_LB": {
        "status": "PASS",
        "count": 31,
        "reasons": []
      },
      "AZURE_PUBLIC_IPADDRESSES": {
        "status": "PASS",
        "count": 23,
        "reasons": []
      },
      "AZURE_EXPRESSROUTE_CIRCUITS": {
        "status": "PASS",
        "count": 3,
        "reasons": []
      },
      "AZURE_STORAGE_ACCOUNT": {
        "status": "WARN",
        "count": 153,
        "reasons": [
          "metric 'summary|usedCapacity' absent on every object (optional)"
        ]
      },
      "AZURE_KEY_VAULTS": {
        "status": "PASS",
        "count": 86,
        "reasons": []
      },
      "AZURE_SQL_SERVER": {
        "status": "PASS",
        "count": 12,
        "reasons": []
      },
      "AZURE_SQL_DATABASE": {
        "status": "PASS",
        "count": 76,
        "reasons": []
      },
      "AZURE_POSTGRESQL_SERVER": {
        "status": "WARN",
        "count": 0,
        "reasons": [
          "no objects (tenant may have none)"
        ]
      },
      "AZURE_MYSQL_SERVER": {
        "status": "WARN",
        "count": 5,
        "reasons": [
          "metric 'CPU_PERCENT' absent on every object (optional)"
        ]
      },
      "AZURE_DB_ACCOUNT": {
        "status": "WARN",
        "count": 0,
        "reasons": [
          "no objects (tenant may have none)"
        ]
      },
      "AZURE_APP_SERVICE": {
        "status": "WARN",
        "count": 6,
        "reasons": [
          "metric 'summary|requests' absent on every object (optional)"
        ]
      },
      "AZURE_FUNCTIONS_APP": {
        "status": "PASS",
        "count": 2,
        "reasons": []
      },
      "AZURE_APP_SERVICE_PLAN": {
        "status": "PASS",
        "count": 6,
        "reasons": []
      },
      "azure_recovery_services_vault": {
        "status": "PASS",
        "count": 110,
        "reasons": []
      },
      "azure_log_analytics_workspace": {
        "status": "PASS",
        "count": 25,
        "reasons": []
      },
      "AZURE_WORLD": {
        "status": "PASS",
        "count": 1,
        "reasons": []
      },
      "AZURE_REGION": {
        "status": "PASS",
        "count": 6,
        "reasons": []
      },
      "AZURE_REGION_PER_SUB": {
        "status": "PASS",
        "count": 6,
        "reasons": []
      },
      "AZURE_VIRTUAL_SCALESET": {
        "status": "PASS",
        "count": 54,
        "reasons": []
      },
      "AZURE_AVAILABILITY_SETS": {
        "status": "PASS",
        "count": 16,
        "reasons": []
      },
      "AZURE_NETWORK_WATCHERS": {
        "status": "PASS",
        "count": 13,
        "reasons": []
      },
      "AZURE_EVENTHUBS_NAMESPACES": {
        "status": "PASS",
        "count": 5,
        "reasons": []
      },
      "AZURE_COGNITIVE_SERVICES_ACCOUNTS": {
        "status": "PASS",
        "count": 3,
        "reasons": []
      },
      "AZURE_SQL_MANAGEDINSTANCES": {
        "status": "PASS",
        "count": 1,
        "reasons": []
      },
      "AZURE_DATA_EXPLORER_CLUSTER": {
        "status": "PASS",
        "count": 1,
        "reasons": []
      },
      "azure_logic_workflow": {
        "status": "PASS",
        "count": 2,
        "reasons": []
      },
      "azure_arc_machine": {
        "status": "PASS",
        "count": 53,
        "reasons": []
      },
      "azure_bastion_host": {
        "status": "PASS",
        "count": 1,
        "reasons": []
      },
      "azure_private_endpoint": {
        "status": "PASS",
        "count": 75,
        "reasons": []
      },
      "azure_nat_gateway": {
        "status": "PASS",
        "count": 3,
        "reasons": []
      },
      "azure_compute_snapshot": {
        "status": "PASS",
        "count": 117,
        "reasons": []
      },
      "azure_disk_encryption_set": {
        "status": "PASS",
        "count": 47,
        "reasons": []
      },
      "azure_managed_identity": {
        "status": "PASS",
        "count": 54,
        "reasons": []
      },
      "azure_dns_resolver": {
        "status": "PASS",
        "count": 9,
        "reasons": []
      },
      "azure_backup_vault": {
        "status": "PASS",
        "count": 1,
        "reasons": []
      },
      "azure_sql_virtual_machine": {
        "status": "PASS",
        "count": 39,
        "reasons": []
      },
      "azure_app_service_environment": {
        "status": "PASS",
        "count": 1,
        "reasons": []
      },
      "azure_storage_sync": {
        "status": "PASS",
        "count": 1,
        "reasons": []
      }
    },
    "dedicated_host_missing_attrs": [
      {
        "missing": [
          "hourly_rate",
          "monthly_rate_estimate",
          "host_vcpu_capacity",
          "total_vm_vcpus_allocated",
          "vcpu_utilization_pct",
          "host_memory_capacity_gb",
          "memory_utilization_pct",
          "memory_available_gb",
          "total_vm_memory_gb",
          "vm_memory_breakdown",
          "vm_count",
          "vm_names",
          "vm_size_summary",
          "vm_size_distinct_count",
          "vm_disk_skus",
          "max_available_slots",
          "smallest_vm_size",
          "smallest_vm_available",
          "allocatable_vm_summary",
          "health_availability_state",
          "health_detailed_status",
          "health_reason_type",
          "health_summary",
          "maintenance_pending",
          "maintenance_impact_type",
          "maintenance_status",
          "cost_month_to_date",
          "cost_currency",
          "cost_last_30_days",
          "advisor_recommendation_count",
          "advisor_recommendations",
          "advisor_impact",
          "advisor_category",
          "recent_operations_count",
          "last_operation",
          "last_operation_time",
          "last_operation_status",
          "last_operation_caller",
          "policy_compliance_state",
          "policy_non_compliant_count",
          "reservation_status",
          "reservation_id",
          "reservation_expiry",
          "time_created",
          "sku_tier",
          "sku_capacity"
        ],
        "host_index": 1
      },
      {
        "missing": [
          "hourly_rate",
          "monthly_rate_estimate",
          "host_vcpu_capacity",
          "total_vm_vcpus_allocated",
          "vcpu_utilization_pct",
          "host_memory_capacity_gb",
          "memory_utilization_pct",
          "memory_available_gb",
          "total_vm_memory_gb",
          "vm_memory_breakdown",
          "vm_count",
          "vm_names",
          "vm_size_summary",
          "vm_size_distinct_count",
          "vm_disk_skus",
          "max_available_slots",
          "smallest_vm_size",
          "smallest_vm_available",
          "allocatable_vm_summary",
          "health_availability_state",
          "health_detailed_status",
          "health_reason_type",
          "health_summary",
          "maintenance_pending",
          "maintenance_impact_type",
          "maintenance_status",
          "cost_month_to_date",
          "cost_currency",
          "cost_last_30_days",
          "advisor_recommendation_count",
          "advisor_recommendations",
          "advisor_impact",
          "advisor_category",
          "recent_operations_count",
          "last_operation",
          "last_operation_time",
          "last_operation_status",
          "last_operation_caller",
          "policy_compliance_state",
          "policy_non_compliant_count",
          "reservation_status",
          "reservation_id",
          "reservation_expiry",
          "time_created",
          "sku_tier",
          "sku_capacity"
        ],
        "host_index": 2
      },
      {
        "missing": [
          "hourly_rate",
          "monthly_rate_estimate",
          "host_vcpu_capacity",
          "total_vm_vcpus_allocated",
          "vcpu_utilization_pct",
          "host_memory_capacity_gb",
          "memory_utilization_pct",
          "memory_available_gb",
          "total_vm_memory_gb",
          "vm_memory_breakdown",
          "vm_count",
          "vm_names",
          "vm_size_summary",
          "vm_size_distinct_count",
          "vm_disk_skus",
          "max_available_slots",
          "smallest_vm_size",
          "smallest_vm_available",
          "allocatable_vm_summary",
          "health_availability_state",
          "health_detailed_status",
          "health_reason_type",
          "health_summary",
          "maintenance_pending",
          "maintenance_impact_type",
          "maintenance_status",
          "cost_month_to_date",
          "cost_currency",
          "cost_last_30_days",
          "advisor_recommendation_count",
          "advisor_recommendations",
          "advisor_impact",
          "advisor_category",
          "recent_operations_count",
          "last_operation",
          "last_operation_time",
          "last_operation_status",
          "last_operation_caller",
          "policy_compliance_state",
          "policy_non_compliant_count",
          "reservation_status",
          "reservation_id",
          "reservation_expiry",
          "time_created",
          "sku_tier",
          "sku_capacity"
        ],
        "host_index": 3
      },
      {
        "missing": [
          "hourly_rate",
          "monthly_rate_estimate",
          "host_vcpu_capacity",
          "total_vm_vcpus_allocated",
          "vcpu_utilization_pct",
          "host_memory_capacity_gb",
          "memory_utilization_pct",
          "memory_available_gb",
          "total_vm_memory_gb",
          "vm_memory_breakdown",
          "vm_count",
          "vm_names",
          "vm_size_summary",
          "vm_size_distinct_count",
          "vm_disk_skus",
          "max_available_slots",
          "smallest_vm_size",
          "smallest_vm_available",
          "allocatable_vm_summary",
          "health_availability_state",
          "health_detailed_status",
          "health_reason_type",
          "health_summary",
          "maintenance_pending",
          "maintenance_impact_type",
          "maintenance_status",
          "cost_month_to_date",
          "cost_currency",
          "cost_last_30_days",
          "advisor_recommendation_count",
          "advisor_recommendations",
          "advisor_impact",
          "advisor_category",
          "recent_operations_count",
          "last_operation",
          "last_operation_time",
          "last_operation_status",
          "last_operation_caller",
          "policy_compliance_state",
          "policy_non_compliant_count",
          "reservation_status",
          "reservation_id",
          "reservation_expiry",
          "time_created",
          "sku_tier",
          "sku_capacity"
        ],
        "host_index": 4
      },
      {
        "missing": [
          "hourly_rate",
          "monthly_rate_estimate",
          "host_vcpu_capacity",
          "total_vm_vcpus_allocated",
          "vcpu_utilization_pct",
          "host_memory_capacity_gb",
          "memory_utilization_pct",
          "memory_available_gb",
          "total_vm_memory_gb",
          "vm_memory_breakdown",
          "vm_count",
          "vm_names",
          "vm_size_summary",
          "vm_size_distinct_count",
          "vm_disk_skus",
          "max_available_slots",
          "smallest_vm_size",
          "smallest_vm_available",
          "allocatable_vm_summary",
          "health_availability_state",
          "health_detailed_status",
          "health_reason_type",
          "health_summary",
          "maintenance_pending",
          "maintenance_impact_type",
          "maintenance_status",
          "cost_month_to_date",
          "cost_currency",
          "cost_last_30_days",
          "advisor_recommendation_count",
          "advisor_recommendations",
          "advisor_impact",
          "advisor_category",
          "recent_operations_count",
          "last_operation",
          "last_operation_time",
          "last_operation_status",
          "last_operation_caller",
          "policy_compliance_state",
          "policy_non_compliant_count",
          "reservation_status",
          "reservation_id",
          "reservation_expiry",
          "time_created",
          "sku_tier",
          "sku_capacity"
        ],
        "host_index": 5
      },
      {
        "missing": [
          "hourly_rate",
          "monthly_rate_estimate",
          "host_vcpu_capacity",
          "total_vm_vcpus_allocated",
          "vcpu_utilization_pct",
          "host_memory_capacity_gb",
          "memory_utilization_pct",
          "memory_available_gb",
          "total_vm_memory_gb",
          "vm_memory_breakdown",
          "vm_count",
          "vm_names",
          "vm_size_summary",
          "vm_size_distinct_count",
          "vm_disk_skus",
          "max_available_slots",
          "smallest_vm_size",
          "smallest_vm_available",
          "allocatable_vm_summary",
          "health_availability_state",
          "health_detailed_status",
          "health_reason_type",
          "health_summary",
          "maintenance_pending",
          "maintenance_impact_type",
          "maintenance_status",
          "cost_month_to_date",
          "cost_currency",
          "cost_last_30_days",
          "advisor_recommendation_count",
          "advisor_recommendations",
          "advisor_impact",
          "advisor_category",
          "recent_operations_count",
          "last_operation",
          "last_operation_time",
          "last_operation_status",
          "last_operation_caller",
          "policy_compliance_state",
          "policy_non_compliant_count",
          "reservation_status",
          "reservation_id",
          "reservation_expiry",
          "time_created",
          "sku_tier",
          "sku_capacity"
        ],
        "host_index": 6
      },
      {
        "missing": [
          "hourly_rate",
          "monthly_rate_estimate",
          "host_vcpu_capacity",
          "total_vm_vcpus_allocated",
          "vcpu_utilization_pct",
          "host_memory_capacity_gb",
          "memory_utilization_pct",
          "memory_available_gb",
          "total_vm_memory_gb",
          "vm_memory_breakdown",
          "vm_count",
          "vm_names",
          "vm_size_summary",
          "vm_size_distinct_count",
          "vm_disk_skus",
          "max_available_slots",
          "smallest_vm_size",
          "smallest_vm_available",
          "allocatable_vm_summary",
          "health_availability_state",
          "health_detailed_status",
          "health_reason_type",
          "health_summary",
          "maintenance_pending",
          "maintenance_impact_type",
          "maintenance_status",
          "cost_month_to_date",
          "cost_currency",
          "cost_last_30_days",
          "advisor_recommendation_count",
          "advisor_recommendations",
          "advisor_impact",
          "advisor_category",
          "recent_operations_count",
          "last_operation",
          "last_operation_time",
          "last_operation_status",
          "last_operation_caller",
          "policy_compliance_state",
          "policy_non_compliant_count",
          "reservation_status",
          "reservation_id",
          "reservation_expiry",
          "time_created",
          "sku_tier",
          "sku_capacity"
        ],
        "host_index": 7
      },
      {
        "missing": [
          "hourly_rate",
          "monthly_rate_estimate",
          "host_vcpu_capacity",
          "total_vm_vcpus_allocated",
          "vcpu_utilization_pct",
          "host_memory_capacity_gb",
          "memory_utilization_pct",
          "memory_available_gb",
          "total_vm_memory_gb",
          "vm_memory_breakdown",
          "vm_count",
          "vm_names",
          "vm_size_summary",
          "vm_size_distinct_count",
          "vm_disk_skus",
          "max_available_slots",
          "smallest_vm_size",
          "smallest_vm_available",
          "allocatable_vm_summary",
          "health_availability_state",
          "health_detailed_status",
          "health_reason_type",
          "health_summary",
          "maintenance_pending",
          "maintenance_impact_type",
          "maintenance_status",
          "cost_month_to_date",
          "cost_currency",
          "cost_last_30_days",
          "advisor_recommendation_count",
          "advisor_recommendations",
          "advisor_impact",
          "advisor_category",
          "recent_operations_count",
          "last_operation",
          "last_operation_time",
          "last_operation_status",
          "last_operation_caller",
          "policy_compliance_state",
          "policy_non_compliant_count",
          "reservation_status",
          "reservation_id",
          "reservation_expiry",
          "time_created",
          "sku_tier",
          "sku_capacity"
        ],
        "host_index": 8
      },
      {
        "missing": [
          "hourly_rate",
          "monthly_rate_estimate",
          "host_vcpu_capacity",
          "total_vm_vcpus_allocated",
          "vcpu_utilization_pct",
          "host_memory_capacity_gb",
          "memory_utilization_pct",
          "memory_available_gb",
          "total_vm_memory_gb",
          "vm_memory_breakdown",
          "vm_count",
          "vm_names",
          "vm_size_summary",
          "vm_size_distinct_count",
          "vm_disk_skus",
          "max_available_slots",
          "smallest_vm_size",
          "smallest_vm_available",
          "allocatable_vm_summary",
          "health_availability_state",
          "health_detailed_status",
          "health_reason_type",
          "health_summary",
          "maintenance_pending",
          "maintenance_impact_type",
          "maintenance_status",
          "cost_month_to_date",
          "cost_currency",
          "cost_last_30_days",
          "advisor_recommendation_count",
          "advisor_recommendations",
          "advisor_impact",
          "advisor_category",
          "recent_operations_count",
          "last_operation",
          "last_operation_time",
          "last_operation_status",
          "last_operation_caller",
          "policy_compliance_state",
          "policy_non_compliant_count",
          "reservation_status",
          "reservation_id",
          "reservation_expiry",
          "time_created",
          "sku_tier",
          "sku_capacity"
        ],
        "host_index": 9
      },
      {
        "missing": [
          "hourly_rate",
          "monthly_rate_estimate",
          "host_vcpu_capacity",
          "total_vm_vcpus_allocated",
          "vcpu_utilization_pct",
          "host_memory_capacity_gb",
          "memory_utilization_pct",
          "memory_available_gb",
          "total_vm_memory_gb",
          "vm_memory_breakdown",
          "vm_count",
          "vm_names",
          "vm_size_summary",
          "vm_size_distinct_count",
          "vm_disk_skus",
          "max_available_slots",
          "smallest_vm_size",
          "smallest_vm_available",
          "allocatable_vm_summary",
          "health_availability_state",
          "health_detailed_status",
          "health_reason_type",
          "health_summary",
          "maintenance_pending",
          "maintenance_impact_type",
          "maintenance_status",
          "cost_month_to_date",
          "cost_currency",
          "cost_last_30_days",
          "advisor_recommendation_count",
          "advisor_recommendations",
          "advisor_impact",
          "advisor_category",
          "recent_operations_count",
          "last_operation",
          "last_operation_time",
          "last_operation_status",
          "last_operation_caller",
          "policy_compliance_state",
          "policy_non_compliant_count",
          "reservation_status",
          "reservation_id",
          "reservation_expiry",
          "time_created",
          "sku_tier",
          "sku_capacity"
        ],
        "host_index": 10
      }
    ]
  },
  "describe_audit": {
    "kind_count": 115,
    "missing_kinds": [],
    "dedicated_host_attrs_missing": [],
    "custom_kinds_with_pipe_attrs": {}
  },
  "content_drift": [
    [
      "/opt/aria/Aria-MP-Builder/Azure-Native-Build/content/traversalspecs/MicrosoftAzureTraversalSpecs.xml",
      "offset 14975",
      "unknown kind AZURE_SYNAPSE_ANALYTICS"
    ],
    [
      "/opt/aria/Aria-MP-Builder/Azure-Native-Build/content/traversalspecs/MicrosoftAzureTraversalSpecs.xml",
      "offset 29861",
      "unknown kind AZURE_SYNAPSE_ANALYTICS"
    ],
    [
      "/opt/aria/Aria-MP-Builder/Azure-Native-Build/content/alertdefs/Microsoft_Azure_Alert_Defs.xml",
      "Condition",
      "unknown attr CPU|CPU_USAGE in @key"
    ],
    [
      "/opt/aria/Aria-MP-Builder/Azure-Native-Build/content/alertdefs/Microsoft_Azure_Alert_Defs.xml",
      "Condition",
      "unknown attr CPU|CPU_USAGE in @key"
    ],
    [
      "/opt/aria/Aria-MP-Builder/Azure-Native-Build/content/alertdefs/Microsoft_Azure_Alert_Defs.xml",
      "Condition",
      "unknown attr CPU|CPU_USAGE in @key"
    ],
    [
      "/opt/aria/Aria-MP-Builder/Azure-Native-Build/content/alertdefs/Microsoft_Azure_Alert_Defs.xml",
      "Condition",
      "unknown attr summary|runtime|powerState in @key"
    ],
    [
      "/opt/aria/Aria-MP-Builder/Azure-Native-Build/content/alertdefs/Microsoft_Azure_Alert_Defs.xml",
      "Condition",
      "unknown attr CPU|CPU_USAGE in @key"
    ],
    [
      "/opt/aria/Aria-MP-Builder/Azure-Native-Build/content/alertdefs/Microsoft_Azure_Alert_Defs.xml",
      "Condition",
      "unknown attr CPU|CPU_USAGE in @key"
    ],
    [
      "/opt/aria/Aria-MP-Builder/Azure-Native-Build/content/alertdefs/Microsoft_Azure_Alert_Defs.xml",
      "Condition",
      "unknown attr CPU|CPU_USAGE in @key"
    ],
    [
      "/opt/aria/Aria-MP-Builder/Azure-Native-Build/content/alertdefs/Microsoft_Azure_Alert_Defs.xml",
      "Condition",
      "unknown attr NETWORK|throughput in @key"
    ],
    [
      "/opt/aria/Aria-MP-Builder/Azure-Native-Build/content/alertdefs/Microsoft_Azure_Alert_Defs.xml",
      "Condition",
      "unknown attr memory|kube_node_status_allocatable_memory_bytes in @key"
    ],
    [
      "/opt/aria/Aria-MP-Builder/Azure-Native-Build/content/alertdefs/Microsoft_Azure_Alert_Defs.xml",
      "Condition",
      "unknown attr summary|availability in @key"
    ],
    [
      "/opt/aria/Aria-MP-Builder/Azure-Native-Build/content/alertdefs/Microsoft_Azure_Alert_Defs.xml",
      "Condition",
      "unknown attr summary|statusOfPrimary in @key"
    ],
    [
      "/opt/aria/Aria-MP-Builder/Azure-Native-Build/content/alertdefs/Microsoft_Azure_Alert_Defs.xml",
      "Condition",
      "unknown attr summary|powerState in @key"
    ],
    [
      "/opt/aria/Aria-MP-Builder/Azure-Native-Build/content/alertdefs/Microsoft_Azure_Alert_Defs.xml",
      "Condition",
      "unknown attr summary|provisioningState in @key"
    ],
    [
      "/opt/aria/Aria-MP-Builder/Azure-Native-Build/content/alertdefs/Microsoft_Azure_Alert_Defs.xml",
      "Condition",
      "unknown attr cpu|percentage_cpu in @key"
    ],
    [
      "/opt/aria/Aria-MP-Builder/Azure-Native-Build/content/alertdefs/Microsoft_Azure_Alert_Defs.xml",
      "Condition",
      "unknown attr summary|provisioningState in @key"
    ],
    [
      "/opt/aria/Aria-MP-Builder/Azure-Native-Build/content/alertdefs/Microsoft_Azure_Alert_Defs.xml",
      "Condition",
      "unknown attr cpu|percentage_cpu in @key"
    ],
    [
      "/opt/aria/Aria-MP-Builder/Azure-Native-Build/content/alertdefs/Microsoft_Azure_Alert_Defs.xml",
      "Condition",
      "unknown attr cpu|percentage_cpu in @key"
    ],
    [
      "/opt/aria/Aria-MP-Builder/Azure-Native-Build/content/alertdefs/Microsoft_Azure_Alert_Defs.xml",
      "Condition",
      "unknown attr summary|state in @key"
    ]
  ],
  "aria_ops": {
    "host": "<aria-ops-host>",
    "kind_count": 115,
    "counts": {
      "AZURE_DATA_EXPLORER_DATABASE": 0,
      "azure_app_service_environment": 1,
      "azure_arc_machine": 702,
      "azure_backup_vault": 1,
      "azure_bastion_host": 1,
      "azure_compute_snapshot": 64,
      "azure_disk_encryption_set": 25,
      "azure_dns_resolver": 6,
      "azure_log_analytics_workspace": 17,
      "azure_logic_workflow": 2,
      "AZURE_SYNAPSE_ANALYTICS_WORKSPACE": 0,
      "azure_managed_identity": 52,
      "azure_nat_gateway": 0,
      "azure_private_endpoint": 78,
      "azure_recovery_services_vault": 217,
      "azure_sql_virtual_machine": 36,
      "azure_storage_sync": 1,
      "azure_subnet": 207,
      "AZURE_SQL_SERVER": 15,
      "azure_subscription": 6,
      "AZURE_POSTGRESQL_SERVER": 0,
      "AZURE_ANALYSIS_SERVICES": 0,
      "AZURE_API_MANAGEMENT": 0,
      "AZURE_APP_CONFIGURATION": 0,
      "AZURE_APP_SERVICE_PLAN": 7,
      "AZURE_AUTOMATION": 21,
      "AZURE_AVAILABILITY_SETS": 12,
      "AZURE_BATCH_ACCOUNT": 0,
      "AZURE_BOT_SERVICES": 0,
      "AZURE_CACHE_REDIS": 4,
      "AZURE_CDN_PROFILES": 0,
      "AZURE_CDN_PROFILES_ENDPOINTS": 0,
      "AZURE_COGNITIVE_SERVICES_ACCOUNTS": 3,
      "AZURE_COMPUTE_DOMAINNAMES": 0,
      "AZURE_COMPUTE_HOSTGROUPS": 23,
      "AZURE_CONTAINER": 0,
      "AZURE_CONTAINER_REGISTRIES": 7,
      "AZURE_CONTIANER_CONTAINERGROUPS": 0,
      "AZURE_DATA_BOX": 0,
      "AZURE_DATALAKE_STORE": 0,
      "AZURE_DDOS_PROTECTION_PLAN": 0,
      "AZURE_DEDICATE_HOST": 381,
      "AZURE_DIGITAL_TWINS": 0,
      "AZURE_DNS_ZONES": 2,
      "AZURE_EVENT_GRID_DOMAIN": 0,
      "AZURE_EVENT_GRID_SUBSCRIPTION": 0,
      "AZURE_EVENT_GRID_TOPIC": 0,
      "AZURE_EVENT_HUBS": 0,
      "AZURE_EVENTHUBS_NAMESPACES": 5,
      "AZURE_EXPRESSROUTE_CIRCUITS": 0,
      "AZURE_FIREWALLS": 0,
      "AZURE_FRONT_DOORS": 0,
      "AZURE_FUNCTIONS_APP": 3,
      "AZURE_IOT_CENTRAL": 0,
      "AZURE_IOT_HUB": 0,
      "AZURE_KEY_VAULTS": 61,
      "AZURE_MACHINE_LEARNING": 0,
      "AZURE_MARIA_DBSERVER_DATABASE": 0,
      "AZURE_MARIADB_SERVER": 0,
      "AZURE_MEDIA_SERVICES": 0,
      "AZURE_MEDIASERVICES_LIVEEVENTS": 0,
      "AZURE_MEDIASERVICES_STREAMINGEP": 0,
      "AZURE_NETAPPACCOUNT": 0,
      "AZURE_NETAPPACCOUNT_CAPACITYPOOLS": 0,
      "AZURE_NETAPPACCOUNT_CAPACITYPOOLS_VOLUMES": 0,
      "AZURE_NETWORK_SECURITY_GROUP": 45,
      "AZURE_NETWORK_WATCHERS": 8,
      "AZURE_NH_NAMESPACES_NOTIFICATIONHUBS": 0,
      "AZURE_NOTIFICATIONHUBS_NAMESPACES": 0,
      "AZURE_OPENSHIFT_CLUSTERS": 0,
      "AZURE_POWER_BI_EMBEDDED": 0,
      "AZURE_PRIVATE_DNSZONES": 83,
      "AZURE_PROXIMITY_PLACEMENT_GROUP": 0,
      "AZURE_PUBLIC_IPADDRESSES": 3,
      "AZURE_PURVIEW_ACCOUNTS": 0,
      "AZURE_REGION": 61,
      "AZURE_REGION_PER_SUB": 14,
      "AZURE_ROUTE_TABLES": 39,
      "AZURE_SEARCH_SERVICES": 0,
      "AZURE_SERVICES_FROM_XML": 0,
      "AZURE_SIGNALR_SERVICES": 0,
      "AZURE_SPATIAL_ANCHORS": 0,
      "AZURE_SQL_MANAGEDINSTANCES": 2,
      "AZURE_SQL_MANAGEDINSTANCES_DATABASE": 0,
      "AZURE_RESOURCE_GROUP": 352,
      "AZURE_STREAM_ANALYTICS_CLUSTERS": 0,
      "AZURE_STREAM_ANALYTICS_JOBS": 0,
      "AZURE_TIME_SERIES_INSIGHTS": 0,
      "AZURE_TRAFFIC_MANAGER_PROFILES": 0,
      "AZURE_VIRTUAL_HUBS": 0,
      "AZURE_VIRTUAL_WAN": 0,
      "AZURE_WORLD": 1,
      "AZURE_VIRTUAL_SCALESET_INSTANCE": 0,
      "AZURE_VIRTUAL_SCALESET": 44,
      "AZURE_KUBERNATE_CLUSTER": 8,
      "AZURE_DATA_FACTORY": 2,
      "AZURE_VIRTUAL_MACHINE": 1140,
      "AZURE_VIRTUAL_NETWORK_GATEWAY": 0,
      "AZURE_APPLICATION_GATEWAY": 1,
      "AZURE_SYNAPSE_ANALYTICS_BIGDATA_POOL": 0,
      "AZURE_VIRTUAL_NETWORK": 31,
      "AZURE_APP_SERVICE": 7,
      "AZURE_DB_ACCOUNT": 0,
      "AZURE_STORAGE_ACCOUNT": 244,
      "MicrosoftAzureAdapter Instance": 3,
      "AZURE_SYNAPSE_ANALYTICS_SQL_POOL": 0,
      "AZURE_STORAGE_DISK": 4431,
      "AZURE_SERVICE_BUS": 0,
      "AZURE_MYSQL_SERVER": 6,
      "AZURE_SQL_DATABASE": 83,
      "AZURE_DATA_LAKE_ANALYTICS": 0,
      "AZURE_DATA_EXPLORER_CLUSTER": 1,
      "AZURE_LB": 17,
      "AZURE_NW_INTERFACE": 2773,
      "AZURE_HDINSIGHT": 0
    },
    "mismatches": [
      "azure_arc_machine: aria=702 live=53",
      "azure_compute_snapshot: aria=64 live=117",
      "azure_disk_encryption_set: aria=25 live=47",
      "azure_dns_resolver: aria=6 live=9",
      "azure_log_analytics_workspace: aria=17 live=25",
      "azure_nat_gateway: aria=0 live=3",
      "azure_recovery_services_vault: aria=217 live=110",
      "azure_subnet: aria=207 live=338",
      "AZURE_SQL_SERVER: aria=15 live=12",
      "AZURE_AVAILABILITY_SETS: aria=12 live=16",
      "AZURE_COMPUTE_HOSTGROUPS: aria=23 live=1",
      "AZURE_DEDICATE_HOST: aria=381 live=10",
      "AZURE_EXPRESSROUTE_CIRCUITS: aria=0 live=3",
      "AZURE_FIREWALLS: aria=0 live=3",
      "AZURE_KEY_VAULTS: aria=61 live=86",
      "AZURE_NETWORK_SECURITY_GROUP: aria=45 live=101",
      "AZURE_NETWORK_WATCHERS: aria=8 live=13",
      "AZURE_PUBLIC_IPADDRESSES: aria=3 live=23",
      "AZURE_REGION: aria=61 live=6",
      "AZURE_REGION_PER_SUB: aria=14 live=6",
      "AZURE_ROUTE_TABLES: aria=39 live=79",
      "AZURE_RESOURCE_GROUP: aria=352 live=528",
      "AZURE_VIRTUAL_HUBS: aria=0 live=2",
      "AZURE_VIRTUAL_SCALESET: aria=44 live=54",
      "AZURE_VIRTUAL_MACHINE: aria=1140 live=219",
      "AZURE_VIRTUAL_NETWORK_GATEWAY: aria=0 live=2",
      "AZURE_VIRTUAL_NETWORK: aria=31 live=44",
      "AZURE_STORAGE_ACCOUNT: aria=244 live=153",
      "AZURE_STORAGE_DISK: aria=4431 live=180",
      "AZURE_LB: aria=17 live=31",
      "AZURE_NW_INTERFACE: aria=2773 live=159"
    ]
  },
  "exit_summary": "FAIL"
}